fileinteract/__init__.py
fileinteract-0.1.0.dist-info/licenses/LICENSE
fileinteract-0.1.0.dist-info/METADATA
fileinteract-0.1.0.dist-info/WHEEL
fileinteract-0.1.0.dist-info/top_level.txt
fileinteract-0.1.0.dist-info/RECORD
