Metadata-Version: 2.4
Name: fileinteract
Version: 0.1.0
Summary: A simple lib to interact with files in Python
Author-email: Guillaume Plagier <ranswnry@gmail.com>
License-Expression: MIT
Requires-Python: >=3.9
License-File: LICENSE
Dynamic: license-file
